poetry_plugin_mono_repo_deps/__init__.py
poetry_plugin_mono_repo_deps/_version.py
poetry_plugin_mono_repo_deps/plugin.py
poetry_plugin_mono_repo_deps/py.typed
poetry_plugin_mono_repo_deps-0.3.3.dist-info/METADATA
poetry_plugin_mono_repo_deps-0.3.3.dist-info/WHEEL
poetry_plugin_mono_repo_deps-0.3.3.dist-info/entry_points.txt
poetry_plugin_mono_repo_deps-0.3.3.dist-info/licenses/LICENSE
poetry_plugin_mono_repo_deps-0.3.3.dist-info/RECORD
