Metadata-Version: 2.4
Name: poetry-plugin-mono-repo-deps
Version: 0.3.3
Summary: Poetry plugin to replace path dependencies in mono repos with named dependency specifications at build time
License: MIT
License-File: LICENSE
Keywords: packaging,poetry
Author: Gerben Oostra
Author-email: ynnx1wmd@duck.com
Requires-Python: >=3.8,<4.0
Classifier: License :: OSI Approved :: MIT License
Classifier: Programming Language :: Python :: 3
Classifier: Programming Language :: Python :: 3.8
Classifier: Programming Language :: Python :: 3.9
Classifier: Programming Language :: Python :: 3.10
Classifier: Programming Language :: Python :: 3.11
Classifier: Programming Language :: Python :: 3.12
Classifier: Programming Language :: Python :: 3.13
Classifier: Programming Language :: Python :: 3.14
Classifier: Topic :: Software Development :: Build Tools
Classifier: Topic :: Software Development :: Libraries :: Python Modules
Requires-Dist: cffi (>=1.12,<2.0.0) ; python_version < "3.9"
Requires-Dist: cffi (>=1.17.0) ; python_version >= "3.13"
Requires-Dist: poetry (>=1.7.0)
Requires-Dist: poetry-core (>=1.7.0)
Project-URL: Homepage, https://github.com/gerbenoostra/poetry-plugin-mono-repo-deps
Project-URL: Repository, https://github.com/gerbenoostra/poetry-plugin-mono-repo-deps
